qube_nic/__init__.py
qube_nic/config.json
qube_nic/configuration.json
qube_nic/eeprom.py
qube_nic/flasher.py
qube_nic/menu.tcss
qube_nic/ui.py
qube_nic/wifi-nic-r3-v2.5.2.bin
qube_nic-0.3.0.dist-info/METADATA
qube_nic-0.3.0.dist-info/WHEEL
qube_nic-0.3.0.dist-info/entry_points.txt
qube_nic-0.3.0.dist-info/RECORD
