Metadata-Version: 2.1
Name: qube_nic
Version: 0.3.0
Summary: NIC tool for flashing NICs
Author: Apoorva Singh
Author-email: apoorvasingh157@gmail.com
Requires-Python: >=3.11,<4.0
Classifier: Programming Language :: Python :: 3
Classifier: Programming Language :: Python :: 3.11
Classifier: Programming Language :: Python :: 3.12
Classifier: Programming Language :: Python :: 3.13
Requires-Dist: esptool (>=4.8.1,<5.0.0)
Requires-Dist: nuitka (>=2.4.11,<3.0.0)
Requires-Dist: rich (>=13.9.4,<14.0.0)
Requires-Dist: textual (>=0.87.1,<0.88.0)
Requires-Dist: textual-dev (>=1.7.0,<2.0.0)
